{
	"name": "oracleoutput",
	"properties": {
		"linkedServiceName": {
			"referenceName": "lsdevsecdatafactoryendtoend",
			"type": "LinkedServiceReference"
		},
		"annotations": [],
		"type": "DelimitedText",
		"typeProperties": {
			"location": {
				"type": "AzureBlobStorageLocation",
				"fileName": "contacts.csv",
				"container": "oracleoutput"
			},
			"columnDelimiter": ",",
			"compressionCodec": "snappy",
			"compressionLevel": "Fastest",
			"escapeChar": "\\",
			"quoteChar": "\""
		},
		"schema": []
	}
}